ruyi/__init__.py
ruyi/__main__.py
ruyi/cli/__init__.py
ruyi/cli/builtin_commands.py
ruyi/cli/cmd.py
ruyi/cli/completer.py
ruyi/cli/completion.py
ruyi/cli/config_cli.py
ruyi/cli/main.py
ruyi/cli/oobe.py
ruyi/cli/self_cli.py
ruyi/cli/user_input.py
ruyi/cli/version_cli.py
ruyi/config/__init__.py
ruyi/config/editor.py
ruyi/config/errors.py
ruyi/config/news.py
ruyi/config/schema.py
ruyi/device/__init__.py
ruyi/device/provision.py
ruyi/device/provision_cli.py
ruyi/log/__init__.py
ruyi/mux/__init__.py
ruyi/mux/runtime.py
ruyi/mux/venv/__init__.py
ruyi/mux/venv/emulator_cfg.py
ruyi/mux/venv/maker.py
ruyi/mux/venv/venv_cli.py
ruyi/mux/venv_cfg.py
ruyi/pluginhost/__init__.py
ruyi/pluginhost/api.py
ruyi/pluginhost/ctx.py
ruyi/pluginhost/paths.py
ruyi/pluginhost/plugin_cli.py
ruyi/pluginhost/unsandboxed.py
ruyi/py.typed
ruyi/resource_bundle/__init__.py
ruyi/resource_bundle/__main__.py
ruyi/resource_bundle/data.py
ruyi/ruyipkg/__init__.py
ruyi/ruyipkg/admin_checksum.py
ruyi/ruyipkg/admin_cli.py
ruyi/ruyipkg/atom.py
ruyi/ruyipkg/augmented_pkg.py
ruyi/ruyipkg/canonical_dump.py
ruyi/ruyipkg/checksum.py
ruyi/ruyipkg/cli_completion.py
ruyi/ruyipkg/distfile.py
ruyi/ruyipkg/entity.py
ruyi/ruyipkg/entity_cli.py
ruyi/ruyipkg/entity_provider.py
ruyi/ruyipkg/fetcher.py
ruyi/ruyipkg/host.py
ruyi/ruyipkg/install.py
ruyi/ruyipkg/install_cli.py
ruyi/ruyipkg/list.py
ruyi/ruyipkg/list_cli.py
ruyi/ruyipkg/list_filter.py
ruyi/ruyipkg/msg.py
ruyi/ruyipkg/news.py
ruyi/ruyipkg/news_cli.py
ruyi/ruyipkg/news_store.py
ruyi/ruyipkg/pkg_manifest.py
ruyi/ruyipkg/profile.py
ruyi/ruyipkg/profile_cli.py
ruyi/ruyipkg/protocols.py
ruyi/ruyipkg/repo.py
ruyi/ruyipkg/state.py
ruyi/ruyipkg/unpack.py
ruyi/ruyipkg/unpack_method.py
ruyi/ruyipkg/update_cli.py
ruyi/telemetry/__init__.py
ruyi/telemetry/aggregate.py
ruyi/telemetry/event.py
ruyi/telemetry/provider.py
ruyi/telemetry/scope.py
ruyi/telemetry/store.py
ruyi/telemetry/telemetry_cli.py
ruyi/utils/__init__.py
ruyi/utils/ar.py
ruyi/utils/ci.py
ruyi-0.44.0.dist-info/METADATA
ruyi-0.44.0.dist-info/WHEEL
ruyi-0.44.0.dist-info/entry_points.txt
ruyi-0.44.0.dist-info/licenses/LICENSE-Apache.txt
ruyi-0.44.0.dist-info/RECORD
