Metadata-Version: 2.4
Name: ruyi
Version: 0.44.0
Summary: Package manager for RuyiSDK
License: Apache License
License-File: LICENSE-Apache.txt
Keywords: ruyi,ruyisdk
Author: WANG Xuerui
Author-email: wangxuerui@iscas.ac.cn
Requires-Python: >=3.10
Classifier: Development Status :: 3 - Alpha
Classifier: Environment :: Console
Classifier: Intended Audience :: Developers
Classifier: License :: OSI Approved :: Apache Software License
Classifier: Operating System :: POSIX :: Linux
Classifier: Programming Language :: Python :: 3.10
Classifier: Programming Language :: Python :: 3.11
Classifier: Programming Language :: Python :: 3.12
Classifier: Programming Language :: Python :: 3.13
Classifier: Programming Language :: Python :: 3.14
Classifier: Topic :: Software Development :: Build Tools
Classifier: Topic :: Software Development :: Embedded Systems
Classifier: Topic :: System :: Software Distribution
Classifier: Typing :: Typed
Requires-Dist: argcomplete (>=2.0.0)
Requires-Dist: arpy
Requires-Dist: fastjsonschema (>=2.15.1)
Requires-Dist: jinja2 (>=3,<4)
Requires-Dist: pygit2 (>=1.6) ; python_version >= "3.11"
Requires-Dist: pygit2 (>=1.6,<1.19) ; python_version < "3.11"
Requires-Dist: pyyaml (>=5.4)
Requires-Dist: requests (>=2,<3)
Requires-Dist: rich (>=11.2.0)
Requires-Dist: semver (>=2.10)
Requires-Dist: tomli (>=1.2) ; python_version < "3.11"
Requires-Dist: tomlkit (>=0.9)
Requires-Dist: tzdata ; sys_platform == "win32"
Project-URL: Documentation, https://ruyisdk.org/docs/intro
Project-URL: Homepage, https://ruyisdk.org
Project-URL: Repository, https://github.com/ruyisdk/ruyi.git
Project-URL: download, https://ruyisdk.org/download
Project-URL: github, https://github.com/ruyisdk/ruyi
Project-URL: issues, https://github.com/ruyisdk/ruyi/issues
